[{
  "_id": {
    "$oid": "61f3edf62a41741ed3bbecdc"
  },
  "name": "HTML",
  "description": "Introduction à l'utilisation du HTML",
  "level": 1,
  "created_at": {
    "$date": "2022-01-28T13:21:58.425Z"
  },
  "edited_at": {
    "$date": "2022-01-28T13:21:58.425Z"
  }
},{
  "_id": {
    "$oid": "61f3ee4d2a41741ed3bbece0"
  },
  "name": "Les balises",
  "description": "Introduction à l'utilisation des balises en HTML",
  "level": 1,
  "parentTheme": {
    "$oid": "61f3edf62a41741ed3bbecdc"
  },
  "created_at": {
    "$date": "2022-01-28T13:23:25.327Z"
  },
  "edited_at": {
    "$date": "2022-01-28T13:23:25.327Z"
  }
},{
  "_id": {
    "$oid": "61f3ee7d2a41741ed3bbece4"
  },
  "name": "CSS",
  "description": "Introduction à l'utilisation du CSS",
  "level": 2,
  "created_at": {
    "$date": "2022-01-28T13:24:13.683Z"
  },
  "edited_at": {
    "$date": "2022-01-28T13:24:13.683Z"
  }
},{
  "_id": {
    "$oid": "61f7b939c6ea39b8dea93c26"
  },
  "name": "Les attributs",
  "description": "Introduction à l'utilisation des attributs",
  "level": 1,
  "parentTheme": {
    "$oid": "61f3edf62a41741ed3bbecdc"
  },
  "created_at": {
    "$date": "2022-01-31T10:26:01.458Z"
  },
  "edited_at": {
    "$date": "2022-01-31T10:26:01.458Z"
  }
},{
  "_id": {
    "$oid": "61fbf54d79fc6289e6d4d0eb"
  },
  "name": "Javascript",
  "description": "Introduction à l'utilisation du Javascript",
  "level": 3,
  "created_at": {
    "$date": "2022-02-03T15:31:25.846Z"
  },
  "edited_at": {
    "$date": "2022-02-03T15:31:25.846Z"
  }
},{
  "_id": {
    "$oid": "61fceae3af2e8cb02910d41c"
  },
  "name": "La structure",
  "description": "Apprentissage de la structure du code HTML",
  "level": 2,
  "parentTheme": {
    "$oid": "61f3edf62a41741ed3bbecdc"
  },
  "created_at": {
    "$date": "2022-02-04T08:59:15.766Z"
  },
  "edited_at": {
    "$date": "2022-02-04T08:59:15.766Z"
  }
}]